vit3l/__init__.py
vit3l/__main__.py
vit3l/browsers.py
vit3l/chrome.py
vit3l/edge.py
vit3l/eel.js
vit3l/electron.py
vit3l/msIE.py
vit3l/py.typed
vit3l/types.py
vit3l-0.22.0.dist-info/licenses/LICENSE
vit3l-0.22.0.dist-info/METADATA
vit3l-0.22.0.dist-info/WHEEL
vit3l-0.22.0.dist-info/entry_points.txt
vit3l-0.22.0.dist-info/top_level.txt
vit3l-0.22.0.dist-info/RECORD
