Metadata-Version: 2.4
Name: Vit3l
Version: 0.22.0
Summary: Fork of Eel with Vite HMR support for modern web development
Home-page: https://github.com/JuanBrotenelle/vit3l
Author: Juan Brotenelle
Author-email: Juan Brotenelle <andrey.evstratenkov@mail.ru>
Maintainer-email: Juan Brotenelle <andrey.evstratenkov@mail.ru>
License-Expression: MIT
Project-URL: Homepage, https://github.com/JuanBrotenelle/vit3l
Project-URL: Documentation, https://github.com/JuanBrotenelle/vit3l#readme
Project-URL: Repository, https://github.com/JuanBrotenelle/vit3l
Project-URL: Issues, https://github.com/JuanBrotenelle/vit3l/issues
Project-URL: Changelog, https://github.com/JuanBrotenelle/vit3l/blob/main/CHANGELOG.md
Keywords: gui,html,javascript,electron,vite,hmr,webpack
Classifier: Development Status :: 4 - Beta
Classifier: Intended Audience :: Developers
Classifier: Operating System :: OS Independent
Classifier: Programming Language :: Python :: 3
Classifier: Programming Language :: Python :: 3.7
Classifier: Programming Language :: Python :: 3.8
Classifier: Programming Language :: Python :: 3.9
Classifier: Programming Language :: Python :: 3.10
Classifier: Programming Language :: Python :: 3.11
Classifier: Programming Language :: Python :: 3.12
Classifier: Programming Language :: Python :: Implementation :: CPython
Classifier: Topic :: Software Development :: Libraries :: Python Modules
Classifier: Topic :: Software Development :: User Interfaces
Classifier: Topic :: Internet :: WWW/HTTP :: Dynamic Content
Requires-Python: >=3.7
License-File: LICENSE
Requires-Dist: bottle>=0.12.0
Requires-Dist: bottle-websocket>=0.2.0
Requires-Dist: future>=0.18.0
Requires-Dist: pyparsing>=2.0.0
Requires-Dist: typing-extensions>=4.0.0
Requires-Dist: importlib-resources>=5.0.0
Requires-Dist: build>=0.10.0
Requires-Dist: twine>=4.0.2
Provides-Extra: jinja2
Requires-Dist: jinja2>=2.10; extra == "jinja2"
Provides-Extra: dev
Requires-Dist: pytest>=6.0; extra == "dev"
Requires-Dist: pytest-cov>=2.0; extra == "dev"
Requires-Dist: black>=22.0; extra == "dev"
Requires-Dist: flake8>=4.0; extra == "dev"
Requires-Dist: mypy>=0.900; extra == "dev"
Requires-Dist: pre-commit>=2.0; extra == "dev"
Dynamic: author
Dynamic: home-page
Dynamic: license-file
Dynamic: requires-python
